logandprint/__init__.py
logandprint/main.py
logandprint-1.2.3.dist-info/LICENSE
logandprint-1.2.3.dist-info/METADATA
logandprint-1.2.3.dist-info/WHEEL
logandprint-1.2.3.dist-info/top_level.txt
logandprint-1.2.3.dist-info/RECORD
